ipybbycell/__init__.py
ipybbycell/_frontend.py
ipybbycell/_version.py
ipybbycell/example.py
ipybbycell/nbextension/extension.js
ipybbycell/nbextension/extension.js.LICENSE.txt
ipybbycell/nbextension/extension.js.map
ipybbycell/tests/__init__.py
ipybbycell/tests/conftest.py
ipybbycell/tests/test_example.py
ipybbycell/tests/test_nbextension_path.py
ipybbycell-0.4.0.data/data/etc/jupyter/nbconfig/notebook.d/ipybbycell.json
ipybbycell-0.4.0.data/data/share/jupyter/labextensions/ipybbycell/install.json
ipybbycell-0.4.0.data/data/share/jupyter/nbextensions/ipybbycell/extension.js
ipybbycell-0.4.0.data/data/share/jupyter/nbextensions/ipybbycell/extension.js.LICENSE.txt
ipybbycell-0.4.0.data/data/share/jupyter/nbextensions/ipybbycell/extension.js.map
ipybbycell-extension/__init__.py
ipybbycell-extension/_frontend.py
ipybbycell-extension/_version.py
ipybbycell-extension/example.py
ipybbycell-extension/nbextension/extension.js
ipybbycell-extension/nbextension/extension.js.LICENSE.txt
ipybbycell-extension/nbextension/extension.js.map
ipybbycell-extension/tests/__init__.py
ipybbycell-extension/tests/conftest.py
ipybbycell-extension/tests/test_example.py
ipybbycell-extension/tests/test_nbextension_path.py
ipybbycell-0.4.0.dist-info/LICENSE.txt
ipybbycell-0.4.0.dist-info/METADATA
ipybbycell-0.4.0.dist-info/WHEEL
ipybbycell-0.4.0.dist-info/top_level.txt
ipybbycell-0.4.0.dist-info/RECORD
